{"nickname":"news","startTimeUtc":"2023-06-08T20:34:40.8245548Z","tournament":{"players":[{"playerId":"5ee958f607039a72c8609710","playerName":"sunkencity64","totalPoints":76001,"games":[{"gamePoints":18238},{"gamePoints":15195},{"gamePoints":17293},{"gamePoints":11943},{"gamePoints":13332}]},{"playerId":"561e6e8afeb81545584f5c42","playerName":"Sagittarius998","totalPoints":74718,"games":[{"gamePoints":null},{"gamePoints":15412},{"gamePoints":20006},{"gamePoints":19479},{"gamePoints":19821}]},{"playerId":"5a90a2f198cc2c6744a8d6b2","playerName":"cep","totalPoints":65861,"games":[{"gamePoints":null},{"gamePoints":21686},{"gamePoints":23876},{"gamePoints":20299},{"gamePoints":null}]},{"playerId":"633342fdc47eb0d4a0b70f24","playerName":"joseph","totalPoints":64321,"games":[{"gamePoints":19333},{"gamePoints":23154},{"gamePoints":null},{"gamePoints":21834},{"gamePoints":null}]},{"playerId":"56af8726f0f544f19cb8a9ea","playerName":"sgminer21","totalPoints":62727,"games":[{"gamePoints":14799},{"gamePoints":14852},{"gamePoints":23169},{"gamePoints":9907},{"gamePoints":null}]},{"playerId":"5c04ec3b43196563803ba61f","playerName":"[Y4] [Y4] [Y4] [Y4] [Y4] [Y4]","totalPoints":45654,"games":[{"gamePoints":null},{"gamePoints":21809},{"gamePoints":23845},{"gamePoints":null},{"gamePoints":null}]},{"playerId":"5eea5f1162df1243a0cdd8e4","playerName":"Vell","totalPoints":43688,"games":[{"gamePoints":null},{"gamePoints":21630},{"gamePoints":null},{"gamePoints":22058},{"gamePoints":null}]},{"playerId":"5e89f4aed51dd63d6819118c","playerName":"TimSchnitzel","totalPoints":39124,"games":[{"gamePoints":null},{"gamePoints":null},{"gamePoints":null},{"gamePoints":22040},{"gamePoints":17084}]},{"playerId":"5718f7db91e037dcd4b9c02c","playerName":"Ben Savage","totalPoints":27430,"games":[{"gamePoints":null},{"gamePoints":16409},{"gamePoints":null},{"gamePoints":11021},{"gamePoints":null}]},{"playerId":"601da7dc848235000143b04d","playerName":"crayz_grace","totalPoints":22262,"games":[{"gamePoints":null},{"gamePoints":12237},{"gamePoints":10025},{"gamePoints":null},{"gamePoints":null}]},{"playerId":"5ffcdd1cd5a65b0001e4713b","playerName":"Tjay","totalPoints":22046,"games":[{"gamePoints":null},{"gamePoints":null},{"gamePoints":null},{"gamePoints":22046},{"gamePoints":null}]},{"playerId":"5e99af0a97d6cf5854da8470","playerName":"slashP","totalPoints":20395,"games":[{"gamePoints":null},{"gamePoints":20395},{"gamePoints":null},{"gamePoints":null},{"gamePoints":null}]},{"playerId":"5c4cb5303d925b4af4b898ec","playerName":"MrYog ","totalPoints":18528,"games":[{"gamePoints":18528},{"gamePoints":null},{"gamePoints":null},{"gamePoints":null},{"gamePoints":null}]},{"playerId":"5803989a090ec63e2890e604","playerName":"simonpdowling","totalPoints":10327,"games":[{"gamePoints":null},{"gamePoints":10327},{"gamePoints":null},{"gamePoints":null},{"gamePoints":null}]},{"playerId":"607d970fb21d5e000148eb89","playerName":"Yazzmercedes","totalPoints":7901,"games":[{"gamePoints":null},{"gamePoints":7901},{"gamePoints":null},{"gamePoints":null},{"gamePoints":null}]}]},"games":[{"allGuesses":[[{"playerName":"Sagittarius998","playerId":"561e6e8afeb81545584f5c42","roundScoreInPoints":3086,"distanceInMeters":894450.0683745024,"time":9,"lat":37.03516686912802,"lng":-120.02143689930253},{"playerName":"TimSchnitzel","playerId":"5e89f4aed51dd63d6819118c","roundScoreInPoints":3216,"distanceInMeters":818005.599200915,"time":10,"lat":39.99133101391765,"lng":-113.95416809789282},{"playerName":"sunkencity64","playerId":"5ee958f607039a72c8609710","roundScoreInPoints":2903,"distanceInMeters":1007998.1371514674,"time":8,"lat":41.58206050652189,"lng":-114.80785870765318}],[{"playerName":"Sagittarius998","playerId":"561e6e8afeb81545584f5c42","roundScoreInPoints":4330,"distanceInMeters":266674.7145845636,"time":10,"lat":50.09253329993532,"lng":15.233131675414926},{"playerName":"TimSchnitzel","playerId":"5e89f4aed51dd63d6819118c","roundScoreInPoints":4090,"distanceInMeters":372194.7828526735,"time":5,"lat":51.95707828886976,"lng":19.038921175480755},{"playerName":"sunkencity64","playerId":"5ee958f607039a72c8609710","roundScoreInPoints":3396,"distanceInMeters":716850.0807073875,"time":6,"lat":54.38266021215746,"lng":22.948681003801326}],[{"playerName":"Sagittarius998","playerId":"561e6e8afeb81545584f5c42","roundScoreInPoints":4551,"distanceInMeters":174268.3877905562,"time":9,"lat":40.08189866407381,"lng":16.20708781851732},{"playerName":"TimSchnitzel","playerId":"5e89f4aed51dd63d6819118c","roundScoreInPoints":2046,"distanceInMeters":1655908.8659242599,"time":6,"lat":39.32197721371343,"lng":-4.0498637660200165},{"playerName":"sunkencity64","playerId":"5ee958f607039a72c8609710","roundScoreInPoints":2164,"distanceInMeters":1552265.615528505,"time":8,"lat":39.98500668490529,"lng":-3.01098370765319}],[{"playerName":"Sagittarius998","playerId":"561e6e8afeb81545584f5c42","roundScoreInPoints":2922,"distanceInMeters":995407.0332418812,"time":8,"lat":-32.78692946337584,"lng":149.45436374133394},{"playerName":"TimSchnitzel","playerId":"5e89f4aed51dd63d6819118c","roundScoreInPoints":2837,"distanceInMeters":1050232.211399401,"time":7,"lat":-33.646225603760186,"lng":150.3419914482981},{"playerName":"sunkencity64","playerId":"5ee958f607039a72c8609710","roundScoreInPoints":1,"distanceInMeters":15167044.150716886,"time":9,"lat":33.3870787857522,"lng":-94.32963678248592}],[{"playerName":"Sagittarius998","playerId":"561e6e8afeb81545584f5c42","roundScoreInPoints":4932,"distanceInMeters":25520.201785497,"time":9,"lat":43.102994804339964,"lng":19.139243996114836},{"playerName":"TimSchnitzel","playerId":"5e89f4aed51dd63d6819118c","roundScoreInPoints":4895,"distanceInMeters":39337.03808401,"time":5,"lat":42.694995192234096,"lng":19.138593893183668},{"playerName":"sunkencity64","playerId":"5ee958f607039a72c8609710","roundScoreInPoints":4868,"distanceInMeters":49612.9693623732,"time":15,"lat":42.54838699963028,"lng":19.300904590576422}]],"playerGames":[{"player":"Sagittarius998","playerId":"561e6e8afeb81545584f5c42","points":19821,"r1":{"points":3086,"time":9},"r2":{"points":4330,"time":10},"r3":{"points":4551,"time":9},"r4":{"points":2922,"time":8},"r5":{"points":4932,"time":9},"eliminatedInGame":"-","totalDistanceInMeters":2356320.4057770004,"totalTime":45,"pinUrl":"pin/510cc736103570e3237670cff60b68e3.png"},{"player":"TimSchnitzel","playerId":"5e89f4aed51dd63d6819118c","points":17084,"r1":{"points":3216,"time":10},"r2":{"points":4090,"time":5},"r3":{"points":2046,"time":6},"r4":{"points":2837,"time":7},"r5":{"points":4895,"time":5},"eliminatedInGame":"-","totalDistanceInMeters":3935678.4974612594,"totalTime":34,"pinUrl":"pin/de09fd4b8c80415344e0d39c7674a2e8.jpg"},{"player":"sunkencity64","playerId":"5ee958f607039a72c8609710","points":13332,"r1":{"points":2903,"time":8},"r2":{"points":3396,"time":6},"r3":{"points":2164,"time":8},"r4":{"points":1,"time":9},"r5":{"points":4868,"time":15},"eliminatedInGame":null,"totalDistanceInMeters":18493770.95346662,"totalTime":45,"pinUrl":"pin/8ab07260821827d1947dfc4894297cec.png"}],"answers":[{"lat":32.87967480055839,"lng":-111.6106987504768,"countryCode":null,"countryName":null},{"lat":48.654851642174584,"lng":18.181799895137793,"countryCode":null,"countryName":null},{"lat":41.50529839645923,"lng":15.340695483436114,"countryCode":null,"countryName":null},{"lat":-35.13361734988143,"lng":139.0326801500618,"countryCode":null,"countryName":null},{"lat":42.98726194529609,"lng":19.410437173478016,"countryCode":null,"countryName":null}],"mapName":"A Diverse World (Unmaintained)","gameNumber":5,"gameUrl":"https://www.geoguessr.com/results/2t8ohwbTtEWWqSDm","gameId":"2t8ohwbTtEWWqSDm","gameDescription":"60 sec. No move","playedWithEliminations":false,"forbidMoving":true,"forbidRotating":false,"forbidZooming":false,"timeLimit":60},{"allGuesses":[[{"playerName":"Vell","playerId":"5eea5f1162df1243a0cdd8e4","roundScoreInPoints":4487,"distanceInMeters":200614.8569104455,"time":11,"lat":50.36849382498056,"lng":15.321072779351036},{"playerName":"Tjay","playerId":"5ffcdd1cd5a65b0001e4713b","roundScoreInPoints":4442,"distanceInMeters":219135.886995967,"time":11,"lat":49.78378095331996,"lng":15.595553001066264},{"playerName":"TimSchnitzel","playerId":"5e89f4aed51dd63d6819118c","roundScoreInPoints":4215,"distanceInMeters":316523.8778546129,"time":10,"lat":49.98147523566295,"lng":16.985782137240296},{"playerName":"joseph","playerId":"633342fdc47eb0d4a0b70f24","roundScoreInPoints":4471,"distanceInMeters":207150.3784922219,"time":9,"lat":50.18022923544659,"lng":15.450154970127187},{"playerName":"cep","playerId":"5a90a2f198cc2c6744a8d6b2","roundScoreInPoints":4481,"distanceInMeters":203215.9173791622,"time":15,"lat":50.254744114085895,"lng":15.384084057903461},{"playerName":"Sagittarius998","playerId":"561e6e8afeb81545584f5c42","roundScoreInPoints":4445,"distanceInMeters":218051.1584308229,"time":10,"lat":50.14491176471948,"lng":15.606576896443896},{"playerName":"sunkencity64","playerId":"5ee958f607039a72c8609710","roundScoreInPoints":4076,"distanceInMeters":378870.1092208815,"time":8,"lat":53.16536441903794,"lng":14.65196877234864},{"playerName":"Ben Savage","playerId":"5718f7db91e037dcd4b9c02c","roundScoreInPoints":3313,"distanceInMeters":762614.3121804673,"time":6,"lat":44.75404267023887,"lng":19.06604265953431},{"playerName":"sgminer21","playerId":"56af8726f0f544f19cb8a9ea","roundScoreInPoints":4575,"distanceInMeters":164743.2411440516,"time":9,"lat":49.58112520185975,"lng":14.751391148921726}],[{"playerName":"Vell","playerId":"5eea5f1162df1243a0cdd8e4","roundScoreInPoints":4142,"distanceInMeters":349157.67157951,"time":13,"lat":35.171071548573536,"lng":-107.935131661372},{"playerName":"Tjay","playerId":"5ffcdd1cd5a65b0001e4713b","roundScoreInPoints":4255,"distanceInMeters":298843.8621570944,"time":8,"lat":35.548194845607725,"lng":-108.29017065687606},{"playerName":"TimSchnitzel","playerId":"5e89f4aed51dd63d6819118c","roundScoreInPoints":3999,"distanceInMeters":413911.8690153272,"time":14,"lat":37.27266716632511,"lng":-113.94645491399545},{"playerName":"joseph","playerId":"633342fdc47eb0d4a0b70f24","roundScoreInPoints":3772,"distanceInMeters":522239.510050313,"time":7,"lat":42.79266826590977,"lng":-109.36326935548628},{"playerName":"cep","playerId":"5a90a2f198cc2c6744a8d6b2","roundScoreInPoints":3444,"distanceInMeters":691226.4670431764,"time":10,"lat":37.548638131585946,"lng":-117.20023065350159},{"playerName":"Sagittarius998","playerId":"561e6e8afeb81545584f5c42","roundScoreInPoints":4227,"distanceInMeters":311084.7014294676,"time":12,"lat":36.22272920346465,"lng":-111.9664183769991},{"playerName":"sunkencity64","playerId":"5ee958f607039a72c8609710","roundScoreInPoints":3220,"distanceInMeters":815623.1888239069,"time":5,"lat":37.97148894383142,"lng":-118.67397964941422},{"playerName":"Ben Savage","playerId":"5718f7db91e037dcd4b9c02c","roundScoreInPoints":3061,"distanceInMeters":909321.6114522152,"time":6,"lat":37.343407371971324,"lng":-99.05895734046568},{"playerName":"sgminer21","playerId":"56af8726f0f544f19cb8a9ea","roundScoreInPoints":4478,"distanceInMeters":204282.8281336667,"time":9,"lat":38.20417174182354,"lng":-111.69097482266348}],[{"playerName":"Vell","playerId":"5eea5f1162df1243a0cdd8e4","roundScoreInPoints":4851,"distanceInMeters":56157.8381221542,"time":9,"lat":-26.205185221455448,"lng":30.577894092847036},{"playerName":"Tjay","playerId":"5ffcdd1cd5a65b0001e4713b","roundScoreInPoints":4849,"distanceInMeters":56988.8712319073,"time":12,"lat":-26.563554679072922,"lng":31.513050644173905},{"playerName":"TimSchnitzel","playerId":"5e89f4aed51dd63d6819118c","roundScoreInPoints":4912,"distanceInMeters":33008.3215193577,"time":8,"lat":-26.40279310392095,"lng":31.196729902021396},{"playerName":"joseph","playerId":"633342fdc47eb0d4a0b70f24","roundScoreInPoints":4818,"distanceInMeters":68577.1500088798,"time":6,"lat":-26.868204045347884,"lng":31.558061894613342},{"playerName":"cep","playerId":"5a90a2f198cc2c6744a8d6b2","roundScoreInPoints":4929,"distanceInMeters":26686.2272417136,"time":9,"lat":-26.388202938215162,"lng":31.08303881336072},{"playerName":"Sagittarius998","playerId":"561e6e8afeb81545584f5c42","roundScoreInPoints":3381,"distanceInMeters":725174.4866524903,"time":7,"lat":-32.14629068533858,"lng":27.016356779644315},{"playerName":"sunkencity64","playerId":"5ee958f607039a72c8609710","roundScoreInPoints":57,"distanceInMeters":8300678.917491605,"time":16,"lat":47.042453876543505,"lng":44.527142292827655},{"playerName":"Ben Savage","playerId":"5718f7db91e037dcd4b9c02c","roundScoreInPoints":57,"distanceInMeters":8276711.171312634,"time":7,"lat":42.72229393063989,"lng":1.4879176595343102},{"playerName":"sgminer21","playerId":"56af8726f0f544f19cb8a9ea","roundScoreInPoints":31,"distanceInMeters":9401412.873672638,"time":11,"lat":-33.57895460352243,"lng":-70.87746080740675}],[{"playerName":"Vell","playerId":"5eea5f1162df1243a0cdd8e4","roundScoreInPoints":3618,"distanceInMeters":599405.081670683,"time":16,"lat":44.3256211468581,"lng":-72.04688062271154},{"playerName":"Tjay","playerId":"5ffcdd1cd5a65b0001e4713b","roundScoreInPoints":3673,"distanceInMeters":571575.4253746308,"time":16,"lat":44.40974467187319,"lng":-72.62035870765318},{"playerName":"TimSchnitzel","playerId":"5e89f4aed51dd63d6819118c","roundScoreInPoints":4747,"distanceInMeters":96260.3833491,"time":12,"lat":41.49138297034982,"lng":-78.11344754868601},{"playerName":"joseph","playerId":"633342fdc47eb0d4a0b70f24","roundScoreInPoints":4119,"distanceInMeters":359205.3952537228,"time":10,"lat":38.289537696457494,"lng":-80.24049498022636},{"playerName":"cep","playerId":"5a90a2f198cc2c6744a8d6b2","roundScoreInPoints":3548,"distanceInMeters":635733.6207106239,"time":11,"lat":44.00113732495099,"lng":-71.1547575919819},{"playerName":"Sagittarius998","playerId":"561e6e8afeb81545584f5c42","roundScoreInPoints":3496,"distanceInMeters":663236.0416677654,"time":11,"lat":36.30540175882029,"lng":-82.61498837981328},{"playerName":"sunkencity64","playerId":"5ee958f607039a72c8609710","roundScoreInPoints":4579,"distanceInMeters":162950.1443989607,"time":11,"lat":40.7534048002765,"lng":-79.45821571445981},{"playerName":"Ben Savage","playerId":"5718f7db91e037dcd4b9c02c","roundScoreInPoints":3697,"distanceInMeters":559526.7731990776,"time":4,"lat":45.25119970031681,"lng":-74.44958234046568},{"playerName":"sgminer21","playerId":"56af8726f0f544f19cb8a9ea","roundScoreInPoints":791,"distanceInMeters":3418062.0045446195,"time":6,"lat":50.4284771247339,"lng":-119.93010111987772}],[{"playerName":"Vell","playerId":"5eea5f1162df1243a0cdd8e4","roundScoreInPoints":4960,"distanceInMeters":14842.8897322141,"time":17,"lat":-37.71233295828195,"lng":-72.6038242399419},{"playerName":"Tjay","playerId":"5ffcdd1cd5a65b0001e4713b","roundScoreInPoints":4827,"distanceInMeters":65381.7160291105,"time":16,"lat":-37.22230760169156,"lng":-71.98486852567427},{"playerName":"TimSchnitzel","playerId":"5e89f4aed51dd63d6819118c","roundScoreInPoints":4167,"distanceInMeters":337778.9836325997,"time":30,"lat":-34.781463257801654,"lng":-71.1109341967553},{"playerName":"joseph","playerId":"633342fdc47eb0d4a0b70f24","roundScoreInPoints":4654,"distanceInMeters":133036.251892189,"time":9,"lat":-38.77748776713245,"lng":-72.60735127772661},{"playerName":"cep","playerId":"5a90a2f198cc2c6744a8d6b2","roundScoreInPoints":3897,"distanceInMeters":461755.6577949304,"time":6,"lat":-33.69102548214901,"lng":-70.78296697366669},{"playerName":"Sagittarius998","playerId":"561e6e8afeb81545584f5c42","roundScoreInPoints":3930,"distanceInMeters":446116.4673744324,"time":7,"lat":-33.73107993956804,"lng":-71.18262916772873},{"playerName":"sunkencity64","playerId":"5ee958f607039a72c8609710","roundScoreInPoints":11,"distanceInMeters":11412843.241080122,"time":14,"lat":-33.621253054847614,"lng":139.94192339424114},{"playerName":"Ben Savage","playerId":"5718f7db91e037dcd4b9c02c","roundScoreInPoints":893,"distanceInMeters":3193396.8047035416,"time":6,"lat":-8.874902675549027,"lng":-71.63708234046568},{"playerName":"sgminer21","playerId":"56af8726f0f544f19cb8a9ea","roundScoreInPoints":32,"distanceInMeters":9368317.387792265,"time":7,"lat":45.17069414924759,"lng":-90.11823935446404}]],"playerGames":[{"player":"Vell","playerId":"5eea5f1162df1243a0cdd8e4","points":22058,"r1":{"points":4487,"time":11},"r2":{"points":4142,"time":13},"r3":{"points":4851,"time":9},"r4":{"points":3618,"time":16},"r5":{"points":4960,"time":17},"eliminatedInGame":"-","totalDistanceInMeters":1220178.3380150069,"totalTime":67,"pinUrl":"pin/bf5081b17eb001070ae850e26655ad38.png"},{"player":"Tjay","playerId":"5ffcdd1cd5a65b0001e4713b","points":22046,"r1":{"points":4442,"time":11},"r2":{"points":4255,"time":8},"r3":{"points":4849,"time":12},"r4":{"points":3673,"time":16},"r5":{"points":4827,"time":16},"eliminatedInGame":"-","totalDistanceInMeters":1211925.7617887103,"totalTime":63,"pinUrl":"pin/c468dc469127a6bbd6901a177db01d24.png"},{"player":"TimSchnitzel","playerId":"5e89f4aed51dd63d6819118c","points":22040,"r1":{"points":4215,"time":10},"r2":{"points":3999,"time":14},"r3":{"points":4912,"time":8},"r4":{"points":4747,"time":12},"r5":{"points":4167,"time":30},"eliminatedInGame":"-","totalDistanceInMeters":1197483.4353709975,"totalTime":75,"pinUrl":"pin/de09fd4b8c80415344e0d39c7674a2e8.jpg"},{"player":"joseph","playerId":"633342fdc47eb0d4a0b70f24","points":21834,"r1":{"points":4471,"time":9},"r2":{"points":3772,"time":7},"r3":{"points":4818,"time":6},"r4":{"points":4119,"time":10},"r5":{"points":4654,"time":9},"eliminatedInGame":null,"totalDistanceInMeters":1290208.6856973264,"totalTime":42,"pinUrl":"pin/8d83e2b6656dcb6de58d553a9e822aed.png"},{"player":"cep","playerId":"5a90a2f198cc2c6744a8d6b2","points":20299,"r1":{"points":4481,"time":15},"r2":{"points":3444,"time":10},"r3":{"points":4929,"time":9},"r4":{"points":3548,"time":11},"r5":{"points":3897,"time":6},"eliminatedInGame":"-","totalDistanceInMeters":2018617.8901696065,"totalTime":51,"pinUrl":"pin/2f2b6ec66fd554538c2294d4d807e987.png"},{"player":"Sagittarius998","playerId":"561e6e8afeb81545584f5c42","points":19479,"r1":{"points":4445,"time":10},"r2":{"points":4227,"time":12},"r3":{"points":3381,"time":7},"r4":{"points":3496,"time":11},"r5":{"points":3930,"time":7},"eliminatedInGame":"-","totalDistanceInMeters":2363662.855554979,"totalTime":47,"pinUrl":"pin/510cc736103570e3237670cff60b68e3.png"},{"player":"sunkencity64","playerId":"5ee958f607039a72c8609710","points":11943,"r1":{"points":4076,"time":8},"r2":{"points":3220,"time":5},"r3":{"points":57,"time":16},"r4":{"points":4579,"time":11},"r5":{"points":11,"time":14},"eliminatedInGame":null,"totalDistanceInMeters":21070965.60101548,"totalTime":54,"pinUrl":"pin/8ab07260821827d1947dfc4894297cec.png"},{"player":"Ben Savage","playerId":"5718f7db91e037dcd4b9c02c","points":11021,"r1":{"points":3313,"time":6},"r2":{"points":3061,"time":6},"r3":{"points":57,"time":7},"r4":{"points":3697,"time":4},"r5":{"points":893,"time":6},"eliminatedInGame":"-","totalDistanceInMeters":13701570.672847936,"totalTime":29,"pinUrl":"pin/a77d9781f3b21051b3cdbb4d62ceae8b.png"},{"player":"sgminer21","playerId":"56af8726f0f544f19cb8a9ea","points":9907,"r1":{"points":4575,"time":9},"r2":{"points":4478,"time":9},"r3":{"points":31,"time":11},"r4":{"points":791,"time":6},"r5":{"points":32,"time":7},"eliminatedInGame":null,"totalDistanceInMeters":22556818.335287243,"totalTime":42,"pinUrl":"pin/c00414d324e98770adefeef7cef0161e.png"}],"answers":[{"lat":50.01605766986612,"lng":12.557102079010136,"countryCode":null,"countryName":null},{"lat":38.09605675667566,"lng":-109.3587821491714,"countryCode":null,"countryName":null},{"lat":-26.59167482226697,"lng":30.94084333771568,"countryCode":null,"countryName":null},{"lat":40.74836341106786,"lng":-77.52374624725208,"countryCode":null,"countryName":null},{"lat":-37.581405671182914,"lng":-72.57097814366401,"countryCode":null,"countryName":null}],"mapName":"A Diverse World (Unmaintained)","gameNumber":4,"gameUrl":"https://www.geoguessr.com/results/FGdUzhUUXUaErrKx","gameId":"FGdUzhUUXUaErrKx","gameDescription":"60 sec. No move","playedWithEliminations":false,"forbidMoving":true,"forbidRotating":false,"forbidZooming":false,"timeLimit":60},{"allGuesses":[[{"playerName":"cep","playerId":"5a90a2f198cc2c6744a8d6b2","roundScoreInPoints":4648,"distanceInMeters":135137.5195261496,"time":17,"lat":13.745123677473503,"lng":101.12939538748748},{"playerName":"[Y4] [Y4] [Y4] [Y4] [Y4] [Y4]","playerId":"5c04ec3b43196563803ba61f","roundScoreInPoints":4534,"distanceInMeters":181376.2712361117,"time":8,"lat":15.37406675886192,"lng":101.73389001832793},{"playerName":"sgminer21","playerId":"56af8726f0f544f19cb8a9ea","roundScoreInPoints":4914,"distanceInMeters":32158.0465788687,"time":14,"lat":14.336709059320793,"lng":100.35394060517126},{"playerName":"Sagittarius998","playerId":"561e6e8afeb81545584f5c42","roundScoreInPoints":4657,"distanceInMeters":131704.850125456,"time":10,"lat":14.307900515354223,"lng":101.42820478198489},{"playerName":"sunkencity64","playerId":"5ee958f607039a72c8609710","roundScoreInPoints":4219,"distanceInMeters":314682.7849988502,"time":8,"lat":14.245219776090472,"lng":103.1426775847553},{"playerName":"crayz_grace","playerId":"601da7dc848235000143b04d","roundScoreInPoints":4395,"distanceInMeters":239176.9442097678,"time":18,"lat":13.372258250321108,"lng":102.06038900825891}],[{"playerName":"cep","playerId":"5a90a2f198cc2c6744a8d6b2","roundScoreInPoints":4807,"distanceInMeters":72906.0232799674,"time":5,"lat":-26.570905735552014,"lng":28.01751865324932},{"playerName":"[Y4] [Y4] [Y4] [Y4] [Y4] [Y4]","playerId":"5c04ec3b43196563803ba61f","roundScoreInPoints":4867,"distanceInMeters":49791.9757755398,"time":5,"lat":-26.050537495018894,"lng":28.298161353118918},{"playerName":"sgminer21","playerId":"56af8726f0f544f19cb8a9ea","roundScoreInPoints":4856,"distanceInMeters":54275.5952247518,"time":11,"lat":-26.114310755035067,"lng":28.32289267048622},{"playerName":"Sagittarius998","playerId":"561e6e8afeb81545584f5c42","roundScoreInPoints":3155,"distanceInMeters":853161.1247090388,"time":8,"lat":-31.756787897061862,"lng":22.09633498474825},{"playerName":"sunkencity64","playerId":"5ee958f607039a72c8609710","roundScoreInPoints":4701,"distanceInMeters":114240.1718965432,"time":9,"lat":-26.962770454881735,"lng":27.933544400372362},{"playerName":"crayz_grace","playerId":"601da7dc848235000143b04d","roundScoreInPoints":62,"distanceInMeters":8148941.403482845,"time":11,"lat":42.216688219920854,"lng":-1.3522015161297674}],[{"playerName":"cep","playerId":"5a90a2f198cc2c6744a8d6b2","roundScoreInPoints":4986,"distanceInMeters":5320.5006754663,"time":8,"lat":35.764513209952355,"lng":10.808799580760823},{"playerName":"[Y4] [Y4] [Y4] [Y4] [Y4] [Y4]","playerId":"5c04ec3b43196563803ba61f","roundScoreInPoints":4713,"distanceInMeters":109722.9901568471,"time":5,"lat":34.73125763011812,"lng":10.760855797219318},{"playerName":"sgminer21","playerId":"56af8726f0f544f19cb8a9ea","roundScoreInPoints":4655,"distanceInMeters":132588.1794434058,"time":7,"lat":36.78840996161745,"lng":10.166771119755381},{"playerName":"Sagittarius998","playerId":"561e6e8afeb81545584f5c42","roundScoreInPoints":4665,"distanceInMeters":128578.3313583707,"time":8,"lat":36.75045197423902,"lng":10.17264376727522},{"playerName":"sunkencity64","playerId":"5ee958f607039a72c8609710","roundScoreInPoints":4624,"distanceInMeters":144946.8777070434,"time":12,"lat":36.85227563338346,"lng":10.021032988599234},{"playerName":"crayz_grace","playerId":"601da7dc848235000143b04d","roundScoreInPoints":1789,"distanceInMeters":1904893.7351351269,"time":13,"lat":23.462609736388334,"lng":-3.01098370765319}],[{"playerName":"cep","playerId":"5a90a2f198cc2c6744a8d6b2","roundScoreInPoints":4983,"distanceInMeters":6188.3844338237,"time":25,"lat":42.44924171808725,"lng":18.636260115655322},{"playerName":"[Y4] [Y4] [Y4] [Y4] [Y4] [Y4]","playerId":"5c04ec3b43196563803ba61f","roundScoreInPoints":4946,"distanceInMeters":19950.9556648818,"time":6,"lat":42.365892722771505,"lng":18.772041817829198},{"playerName":"sgminer21","playerId":"56af8726f0f544f19cb8a9ea","roundScoreInPoints":4920,"distanceInMeters":30054.4035310482,"time":16,"lat":42.281795181161385,"lng":18.84189480000594},{"playerName":"Sagittarius998","playerId":"561e6e8afeb81545584f5c42","roundScoreInPoints":4920,"distanceInMeters":29731.6421254711,"time":12,"lat":42.287196627372445,"lng":18.842830146448957},{"playerName":"sunkencity64","playerId":"5ee958f607039a72c8609710","roundScoreInPoints":3659,"distanceInMeters":578506.9276851714,"time":28,"lat":38.514930351430884,"lng":23.03132910631596},{"playerName":"crayz_grace","playerId":"601da7dc848235000143b04d","roundScoreInPoints":3763,"distanceInMeters":526591.726442878,"time":16,"lat":47.10708334605615,"lng":17.30986474872935}],[{"playerName":"cep","playerId":"5a90a2f198cc2c6744a8d6b2","roundScoreInPoints":4452,"distanceInMeters":215171.4320106622,"time":11,"lat":23.211468584897986,"lng":-106.2396866803083},{"playerName":"[Y4] [Y4] [Y4] [Y4] [Y4] [Y4]","playerId":"5c04ec3b43196563803ba61f","roundScoreInPoints":4785,"distanceInMeters":81379.5428913818,"time":3,"lat":24.59165998492432,"lng":-104.32696868632628},{"playerName":"sgminer21","playerId":"56af8726f0f544f19cb8a9ea","roundScoreInPoints":3824,"distanceInMeters":497025.0625420146,"time":13,"lat":21.166540842185487,"lng":-100.39246609044764},{"playerName":"Sagittarius998","playerId":"561e6e8afeb81545584f5c42","roundScoreInPoints":2609,"distanceInMeters":1205754.1190246707,"time":9,"lat":17.146577190259247,"lng":-95.15460469831275},{"playerName":"sunkencity64","playerId":"5ee958f607039a72c8609710","roundScoreInPoints":90,"distanceInMeters":7450782.249796472,"time":24,"lat":-14.509816194312425,"lng":-48.01098370765319},{"playerName":"crayz_grace","playerId":"601da7dc848235000143b04d","roundScoreInPoints":16,"distanceInMeters":10665521.94576182,"time":12,"lat":46.7243246508214,"lng":25.114016292346808}]],"playerGames":[{"player":"cep","playerId":"5a90a2f198cc2c6744a8d6b2","points":23876,"r1":{"points":4648,"time":17},"r2":{"points":4807,"time":5},"r3":{"points":4986,"time":8},"r4":{"points":4983,"time":25},"r5":{"points":4452,"time":11},"eliminatedInGame":"-","totalDistanceInMeters":434723.85992606916,"totalTime":67,"pinUrl":"pin/2f2b6ec66fd554538c2294d4d807e987.png"},{"player":"[Y4] [Y4] [Y4] [Y4] [Y4] [Y4]","playerId":"5c04ec3b43196563803ba61f","points":23845,"r1":{"points":4534,"time":8},"r2":{"points":4867,"time":5},"r3":{"points":4713,"time":5},"r4":{"points":4946,"time":6},"r5":{"points":4785,"time":3},"eliminatedInGame":"-","totalDistanceInMeters":442221.7357247622,"totalTime":28,"pinUrl":"pin/1725611c83d93d423fb6b772dbf9e5dd.png"},{"player":"sgminer21","playerId":"56af8726f0f544f19cb8a9ea","points":23169,"r1":{"points":4914,"time":14},"r2":{"points":4856,"time":11},"r3":{"points":4655,"time":7},"r4":{"points":4920,"time":16},"r5":{"points":3824,"time":13},"eliminatedInGame":null,"totalDistanceInMeters":746101.2873200891,"totalTime":61,"pinUrl":"pin/c00414d324e98770adefeef7cef0161e.png"},{"player":"Sagittarius998","playerId":"561e6e8afeb81545584f5c42","points":20006,"r1":{"points":4657,"time":10},"r2":{"points":3155,"time":8},"r3":{"points":4665,"time":8},"r4":{"points":4920,"time":12},"r5":{"points":2609,"time":9},"eliminatedInGame":"-","totalDistanceInMeters":2348930.067343007,"totalTime":47,"pinUrl":"pin/510cc736103570e3237670cff60b68e3.png"},{"player":"sunkencity64","playerId":"5ee958f607039a72c8609710","points":17293,"r1":{"points":4219,"time":8},"r2":{"points":4701,"time":9},"r3":{"points":4624,"time":12},"r4":{"points":3659,"time":28},"r5":{"points":90,"time":24},"eliminatedInGame":null,"totalDistanceInMeters":8603159.01208408,"totalTime":80,"pinUrl":"pin/8ab07260821827d1947dfc4894297cec.png"},{"player":"crayz_grace","playerId":"601da7dc848235000143b04d","points":10025,"r1":{"points":4395,"time":18},"r2":{"points":62,"time":11},"r3":{"points":1789,"time":13},"r4":{"points":3763,"time":16},"r5":{"points":16,"time":12},"eliminatedInGame":"-","totalDistanceInMeters":21485125.755032435,"totalTime":70,"pinUrl":"pin/b434e86f59299c6ef9864bce6c46a251.png"}],"answers":[{"lat":14.60573177528884,"lng":100.2443217786194,"countryCode":null,"countryName":null},{"lat":-25.94086743662541,"lng":27.815139750952767,"countryCode":null,"countryName":null},{"lat":35.71700015408515,"lng":10.81576682689153,"countryCode":null,"countryName":null},{"lat":42.45519067032527,"lng":18.561264752958625,"countryCode":null,"countryName":null},{"lat":23.86298,"lng":-104.25219,"countryCode":null,"countryName":null}],"mapName":"A Diverse World (Unmaintained)","gameNumber":3,"gameUrl":"https://www.geoguessr.com/results/swCnrBEeXw2NfkiS","gameId":"swCnrBEeXw2NfkiS","gameDescription":"60 sec. No move","playedWithEliminations":false,"forbidMoving":true,"forbidRotating":false,"forbidZooming":false,"timeLimit":60},{"allGuesses":[[{"playerName":"joseph","playerId":"633342fdc47eb0d4a0b70f24","roundScoreInPoints":4430,"distanceInMeters":224207.3225617457,"time":13,"lat":14.561555057812194,"lng":121.02356325195147},{"playerName":"[Y4] [Y4] [Y4] [Y4] [Y4] [Y4]","playerId":"5c04ec3b43196563803ba61f","roundScoreInPoints":3651,"distanceInMeters":582803.6635800762,"time":14,"lat":11.819760881504324,"lng":122.76813930155265},{"playerName":"cep","playerId":"5a90a2f198cc2c6744a8d6b2","roundScoreInPoints":3337,"distanceInMeters":749514.2923055468,"time":21,"lat":10.773634488233169,"lng":123.93257899756333},{"playerName":"Vell","playerId":"5eea5f1162df1243a0cdd8e4","roundScoreInPoints":3641,"distanceInMeters":587914.7275322743,"time":24,"lat":12.357413188720178,"lng":123.59509450011195},{"playerName":"slashP","playerId":"5e99af0a97d6cf5854da8470","roundScoreInPoints":4336,"distanceInMeters":263966.2306620598,"time":28,"lat":14.326664769938082,"lng":121.3301221818835},{"playerName":"Ben Savage","playerId":"5718f7db91e037dcd4b9c02c","roundScoreInPoints":4805,"distanceInMeters":73807.0132717989,"time":19,"lat":16.410756631430225,"lng":120.62773432715208},{"playerName":"Sagittarius998","playerId":"561e6e8afeb81545584f5c42","roundScoreInPoints":1049,"distanceInMeters":2893577.2490689415,"time":18,"lat":-5.280681233873194,"lng":105.23448516752379},{"playerName":"sunkencity64","playerId":"5ee958f607039a72c8609710","roundScoreInPoints":1813,"distanceInMeters":1880053.9683011184,"time":18,"lat":14.959095746067986,"lng":102.43995943796267},{"playerName":"sgminer21","playerId":"56af8726f0f544f19cb8a9ea","roundScoreInPoints":1750,"distanceInMeters":1945753.7625161563,"time":17,"lat":1.5318850107334607,"lng":110.40276379415457},{"playerName":"crayz_grace","playerId":"601da7dc848235000143b04d","roundScoreInPoints":4457,"distanceInMeters":213262.7022768545,"time":25,"lat":14.532985863290511,"lng":120.7436785394573},{"playerName":"simonpdowling","playerId":"5803989a090ec63e2890e604","roundScoreInPoints":1362,"distanceInMeters":2409944.5872946223,"time":18,"lat":2.449283772350202,"lng":102.9978361281184},{"playerName":"Yazzmercedes","playerId":"607d970fb21d5e000148eb89","roundScoreInPoints":1616,"distanceInMeters":2093830.5364377685,"time":20,"lat":15.806698332289702,"lng":100.35254644343105}],[{"playerName":"joseph","playerId":"633342fdc47eb0d4a0b70f24","roundScoreInPoints":4814,"distanceInMeters":70191.437436942,"time":8,"lat":14.782876041359877,"lng":102.21360527953904},{"playerName":"[Y4] [Y4] [Y4] [Y4] [Y4] [Y4]","playerId":"5c04ec3b43196563803ba61f","roundScoreInPoints":4797,"distanceInMeters":76869.7765856178,"time":4,"lat":15.56585764264628,"lng":102.78478620976803},{"playerName":"cep","playerId":"5a90a2f198cc2c6744a8d6b2","roundScoreInPoints":4604,"distanceInMeters":152850.33056665,"time":9,"lat":15.794150829475667,"lng":100.71982533730309},{"playerName":"Vell","playerId":"5eea5f1162df1243a0cdd8e4","roundScoreInPoints":4575,"distanceInMeters":164595.7770956301,"time":20,"lat":15.727027719256895,"lng":100.58862544459365},{"playerName":"slashP","playerId":"5e99af0a97d6cf5854da8470","roundScoreInPoints":3315,"distanceInMeters":761693.5467313216,"time":13,"lat":9.107897095505045,"lng":99.32064788596414},{"playerName":"Ben Savage","playerId":"5718f7db91e037dcd4b9c02c","roundScoreInPoints":1493,"distanceInMeters":2240272.407421741,"time":16,"lat":11.050272084227556,"lng":122.30666047575346},{"playerName":"Sagittarius998","playerId":"561e6e8afeb81545584f5c42","roundScoreInPoints":1487,"distanceInMeters":2248311.7226069774,"time":11,"lat":11.230693743938069,"lng":122.42999153377419},{"playerName":"sunkencity64","playerId":"5ee958f607039a72c8609710","roundScoreInPoints":4548,"distanceInMeters":175749.0540919942,"time":7,"lat":15.623619901280083,"lng":103.71195602308595},{"playerName":"sgminer21","playerId":"56af8726f0f544f19cb8a9ea","roundScoreInPoints":1491,"distanceInMeters":2242631.235287281,"time":9,"lat":11.387101328285294,"lng":122.41590709421426},{"playerName":"crayz_grace","playerId":"601da7dc848235000143b04d","roundScoreInPoints":2653,"distanceInMeters":1174778.5050113008,"time":11,"lat":4.840781094418838,"lng":101.81149543575701},{"playerName":"simonpdowling","playerId":"5803989a090ec63e2890e604","roundScoreInPoints":1443,"distanceInMeters":2302938.63305724,"time":15,"lat":12.324368353190168,"lng":123.19309095215635},{"playerName":"Yazzmercedes","playerId":"607d970fb21d5e000148eb89","roundScoreInPoints":3350,"distanceInMeters":742220.185790102,"time":14,"lat":13.514958762124294,"lng":108.70036182013418}],[{"playerName":"joseph","playerId":"633342fdc47eb0d4a0b70f24","roundScoreInPoints":4544,"distanceInMeters":177155.9804247609,"time":7,"lat":-27.821533526093216,"lng":26.581677649121893},{"playerName":"[Y4] [Y4] [Y4] [Y4] [Y4] [Y4]","playerId":"5c04ec3b43196563803ba61f","roundScoreInPoints":4051,"distanceInMeters":389912.3730574092,"time":4,"lat":-30.357500427459826,"lng":25.342053579530123},{"playerName":"cep","playerId":"5a90a2f198cc2c6744a8d6b2","roundScoreInPoints":4789,"distanceInMeters":80001.030782426,"time":10,"lat":-27.333937482862662,"lng":28.278494898547823},{"playerName":"Vell","playerId":"5eea5f1162df1243a0cdd8e4","roundScoreInPoints":4458,"distanceInMeters":212625.5107018926,"time":8,"lat":-26.403740656697448,"lng":27.270893263937772},{"playerName":"slashP","playerId":"5e99af0a97d6cf5854da8470","roundScoreInPoints":4424,"distanceInMeters":227018.2211171299,"time":8,"lat":-26.22582531654272,"lng":27.334321448716018},{"playerName":"Ben Savage","playerId":"5718f7db91e037dcd4b9c02c","roundScoreInPoints":3336,"distanceInMeters":750233.973945326,"time":15,"lat":-33.22225822447661,"lng":23.328515284573438},{"playerName":"Sagittarius998","playerId":"561e6e8afeb81545584f5c42","roundScoreInPoints":3562,"distanceInMeters":628582.8545809957,"time":16,"lat":-30.922291627178982,"lng":22.77204516241403},{"playerName":"sunkencity64","playerId":"5ee958f607039a72c8609710","roundScoreInPoints":63,"distanceInMeters":8116199.038862011,"time":24,"lat":38.8970997497318,"lng":-2.7888368131231944},{"playerName":"sgminer21","playerId":"56af8726f0f544f19cb8a9ea","roundScoreInPoints":2845,"distanceInMeters":1045316.7025552545,"time":9,"lat":-29.957579035435668,"lng":17.837166236371374},{"playerName":"crayz_grace","playerId":"601da7dc848235000143b04d","roundScoreInPoints":1,"distanceInMeters":15288103.2608094,"time":11,"lat":36.60331714057128,"lng":-101.77681831732427},{"playerName":"simonpdowling","playerId":"5803989a090ec63e2890e604","roundScoreInPoints":44,"distanceInMeters":8776926.17880104,"time":10,"lat":-33.18411752921725,"lng":-66.7141666433679},{"playerName":"Yazzmercedes","playerId":"607d970fb21d5e000148eb89","roundScoreInPoints":10,"distanceInMeters":11597415.054496445,"time":21,"lat":-1.492484188167858,"lng":-78.71975560587934}],[{"playerName":"joseph","playerId":"633342fdc47eb0d4a0b70f24","roundScoreInPoints":4784,"distanceInMeters":82007.3920745662,"time":11,"lat":44.552016253374525,"lng":3.5024132364870297},{"playerName":"[Y4] [Y4] [Y4] [Y4] [Y4] [Y4]","playerId":"5c04ec3b43196563803ba61f","roundScoreInPoints":4505,"distanceInMeters":193382.932508332,"time":6,"lat":45.435897747005185,"lng":4.174277695518147},{"playerName":"cep","playerId":"5a90a2f198cc2c6744a8d6b2","roundScoreInPoints":4359,"distanceInMeters":254275.6117521976,"time":6,"lat":45.607187760337,"lng":5.203386646042176},{"playerName":"Vell","playerId":"5eea5f1162df1243a0cdd8e4","roundScoreInPoints":4570,"distanceInMeters":166541.4715309361,"time":15,"lat":44.95938507161778,"lng":4.548428986444346},{"playerName":"slashP","playerId":"5e99af0a97d6cf5854da8470","roundScoreInPoints":3607,"distanceInMeters":605199.5298250093,"time":18,"lat":49.10773329336823,"lng":5.264489285237479},{"playerName":"Ben Savage","playerId":"5718f7db91e037dcd4b9c02c","roundScoreInPoints":3807,"distanceInMeters":505241.2757958481,"time":12,"lat":48.0441814634941,"lng":0.5210902599702338},{"playerName":"Sagittarius998","playerId":"561e6e8afeb81545584f5c42","roundScoreInPoints":4450,"distanceInMeters":216087.0424982798,"time":14,"lat":44.31436627039165,"lng":5.742637907628367},{"playerName":"sunkencity64","playerId":"5ee958f607039a72c8609710","roundScoreInPoints":4036,"distanceInMeters":396878.3460636962,"time":9,"lat":47.439569966912394,"lng":3.02900018001814},{"playerName":"sgminer21","playerId":"56af8726f0f544f19cb8a9ea","roundScoreInPoints":4226,"distanceInMeters":311895.8267109741,"time":12,"lat":46.25001341148917,"lng":5.212013694204343},{"playerName":"crayz_grace","playerId":"601da7dc848235000143b04d","roundScoreInPoints":2205,"distanceInMeters":1517492.2933963456,"time":8,"lat":44.39697840707281,"lng":22.151721888529224},{"playerName":"simonpdowling","playerId":"5803989a090ec63e2890e604","roundScoreInPoints":4137,"distanceInMeters":351190.8988531867,"time":17,"lat":46.48389854054804,"lng":5.62563615535943},{"playerName":"Yazzmercedes","playerId":"607d970fb21d5e000148eb89","roundScoreInPoints":1955,"distanceInMeters":1740781.6093404237,"time":13,"lat":45.66800295869335,"lng":25.084463624066}],[{"playerName":"joseph","playerId":"633342fdc47eb0d4a0b70f24","roundScoreInPoints":4582,"distanceInMeters":161747.491281277,"time":7,"lat":35.898277700059694,"lng":128.52982676144927},{"playerName":"[Y4] [Y4] [Y4] [Y4] [Y4] [Y4]","playerId":"5c04ec3b43196563803ba61f","roundScoreInPoints":4805,"distanceInMeters":73873.1493312827,"time":3,"lat":36.70943341250085,"lng":128.1470765736536},{"playerName":"cep","playerId":"5a90a2f198cc2c6744a8d6b2","roundScoreInPoints":4597,"distanceInMeters":155914.5897618823,"time":6,"lat":36.04663370370878,"lng":129.02951429441742},{"playerName":"Vell","playerId":"5eea5f1162df1243a0cdd8e4","roundScoreInPoints":4386,"distanceInMeters":243040.5206428134,"time":9,"lat":35.380935226623166,"lng":127.19360651874248},{"playerName":"slashP","playerId":"5e99af0a97d6cf5854da8470","roundScoreInPoints":4713,"distanceInMeters":109713.0164984228,"time":5,"lat":36.542390830223596,"lng":127.66448117538144},{"playerName":"Ben Savage","playerId":"5718f7db91e037dcd4b9c02c","roundScoreInPoints":2968,"distanceInMeters":966468.3458964612,"time":7,"lat":37.07458246489431,"lng":139.29188530221597},{"playerName":"Sagittarius998","playerId":"561e6e8afeb81545584f5c42","roundScoreInPoints":4864,"distanceInMeters":50947.3371401901,"time":10,"lat":36.89502003854796,"lng":128.46585432506137},{"playerName":"sunkencity64","playerId":"5ee958f607039a72c8609710","roundScoreInPoints":4735,"distanceInMeters":100911.3100275639,"time":7,"lat":36.51430179531126,"lng":127.9285068856144},{"playerName":"sgminer21","playerId":"56af8726f0f544f19cb8a9ea","roundScoreInPoints":4540,"distanceInMeters":178935.2195135624,"time":8,"lat":35.738572331208026,"lng":128.3752593062163},{"playerName":"crayz_grace","playerId":"601da7dc848235000143b04d","roundScoreInPoints":2921,"distanceInMeters":996123.7067970206,"time":11,"lat":37.26868891017707,"lng":139.64682938537672},{"playerName":"simonpdowling","playerId":"5803989a090ec63e2890e604","roundScoreInPoints":3341,"distanceInMeters":747341.2374975061,"time":16,"lat":34.90344622438877,"lng":136.13235844928073},{"playerName":"Yazzmercedes","playerId":"607d970fb21d5e000148eb89","roundScoreInPoints":970,"distanceInMeters":3039797.662479176,"time":26,"lat":64.43880520005739,"lng":134.5177453247694}]],"playerGames":[{"player":"joseph","playerId":"633342fdc47eb0d4a0b70f24","points":23154,"r1":{"points":4430,"time":13},"r2":{"points":4814,"time":8},"r3":{"points":4544,"time":7},"r4":{"points":4784,"time":11},"r5":{"points":4582,"time":7},"eliminatedInGame":null,"totalDistanceInMeters":715309.6237792919,"totalTime":47,"pinUrl":"pin/8d83e2b6656dcb6de58d553a9e822aed.png"},{"player":"[Y4] [Y4] [Y4] [Y4] [Y4] [Y4]","playerId":"5c04ec3b43196563803ba61f","points":21809,"r1":{"points":3651,"time":14},"r2":{"points":4797,"time":4},"r3":{"points":4051,"time":4},"r4":{"points":4505,"time":6},"r5":{"points":4805,"time":3},"eliminatedInGame":"-","totalDistanceInMeters":1316841.8950627176,"totalTime":31,"pinUrl":"pin/1725611c83d93d423fb6b772dbf9e5dd.png"},{"player":"cep","playerId":"5a90a2f198cc2c6744a8d6b2","points":21686,"r1":{"points":3337,"time":21},"r2":{"points":4604,"time":9},"r3":{"points":4789,"time":10},"r4":{"points":4359,"time":6},"r5":{"points":4597,"time":6},"eliminatedInGame":"-","totalDistanceInMeters":1392555.8551687028,"totalTime":52,"pinUrl":"pin/2f2b6ec66fd554538c2294d4d807e987.png"},{"player":"Vell","playerId":"5eea5f1162df1243a0cdd8e4","points":21630,"r1":{"points":3641,"time":24},"r2":{"points":4575,"time":20},"r3":{"points":4458,"time":8},"r4":{"points":4570,"time":15},"r5":{"points":4386,"time":9},"eliminatedInGame":"-","totalDistanceInMeters":1374718.0075035468,"totalTime":76,"pinUrl":"pin/bf5081b17eb001070ae850e26655ad38.png"},{"player":"slashP","playerId":"5e99af0a97d6cf5854da8470","points":20395,"r1":{"points":4336,"time":28},"r2":{"points":3315,"time":13},"r3":{"points":4424,"time":8},"r4":{"points":3607,"time":18},"r5":{"points":4713,"time":5},"eliminatedInGame":"-","totalDistanceInMeters":1967590.5448339432,"totalTime":72,"pinUrl":"pin/7bb34cfa4431b08534fb01bb09093a1d.png"},{"player":"Ben Savage","playerId":"5718f7db91e037dcd4b9c02c","points":16409,"r1":{"points":4805,"time":19},"r2":{"points":1493,"time":16},"r3":{"points":3336,"time":15},"r4":{"points":3807,"time":12},"r5":{"points":2968,"time":7},"eliminatedInGame":"-","totalDistanceInMeters":4536023.016331175,"totalTime":68,"pinUrl":"pin/a77d9781f3b21051b3cdbb4d62ceae8b.png"},{"player":"Sagittarius998","playerId":"561e6e8afeb81545584f5c42","points":15412,"r1":{"points":1049,"time":18},"r2":{"points":1487,"time":11},"r3":{"points":3562,"time":16},"r4":{"points":4450,"time":14},"r5":{"points":4864,"time":10},"eliminatedInGame":"-","totalDistanceInMeters":6037506.205895385,"totalTime":69,"pinUrl":"pin/510cc736103570e3237670cff60b68e3.png"},{"player":"sunkencity64","playerId":"5ee958f607039a72c8609710","points":15195,"r1":{"points":1813,"time":18},"r2":{"points":4548,"time":7},"r3":{"points":63,"time":24},"r4":{"points":4036,"time":9},"r5":{"points":4735,"time":7},"eliminatedInGame":null,"totalDistanceInMeters":10669791.717346383,"totalTime":65,"pinUrl":"pin/8ab07260821827d1947dfc4894297cec.png"},{"player":"sgminer21","playerId":"56af8726f0f544f19cb8a9ea","points":14852,"r1":{"points":1750,"time":17},"r2":{"points":1491,"time":9},"r3":{"points":2845,"time":9},"r4":{"points":4226,"time":12},"r5":{"points":4540,"time":8},"eliminatedInGame":null,"totalDistanceInMeters":5724532.746583228,"totalTime":55,"pinUrl":"pin/c00414d324e98770adefeef7cef0161e.png"},{"player":"crayz_grace","playerId":"601da7dc848235000143b04d","points":12237,"r1":{"points":4457,"time":25},"r2":{"points":2653,"time":11},"r3":{"points":1,"time":11},"r4":{"points":2205,"time":8},"r5":{"points":2921,"time":11},"eliminatedInGame":"-","totalDistanceInMeters":19189760.46829092,"totalTime":66,"pinUrl":"pin/b434e86f59299c6ef9864bce6c46a251.png"},{"player":"simonpdowling","playerId":"5803989a090ec63e2890e604","points":10327,"r1":{"points":1362,"time":18},"r2":{"points":1443,"time":15},"r3":{"points":44,"time":10},"r4":{"points":4137,"time":17},"r5":{"points":3341,"time":16},"eliminatedInGame":"-","totalDistanceInMeters":14588341.535503594,"totalTime":76,"pinUrl":"pin/b5a2336bed667beaa5cb6b790a773d84.png"},{"player":"Yazzmercedes","playerId":"607d970fb21d5e000148eb89","points":7901,"r1":{"points":1616,"time":20},"r2":{"points":3350,"time":14},"r3":{"points":10,"time":21},"r4":{"points":1955,"time":13},"r5":{"points":970,"time":26},"eliminatedInGame":"-","totalDistanceInMeters":19214045.048543915,"totalTime":93,"pinUrl":"pin/7014ad46a5fd6da3b98e0c2119d8056c.png"}],"answers":[{"lat":16.2906036580203,"lng":119.9474228911967,"countryCode":null,"countryName":null},{"lat":15.40232677664968,"lng":102.0878021314826,"countryCode":null,"countryName":null},{"lat":-28.04916917418138,"lng":28.36652580031614,"countryCode":null,"countryName":null},{"lat":43.870785760127184,"lng":3.108176860766213,"countryCode":null,"countryName":null},{"lat":37.34777424567866,"lng":128.3776802240497,"countryCode":null,"countryName":null}],"mapName":"A Diverse World (Unmaintained)","gameNumber":2,"gameUrl":"https://www.geoguessr.com/results/s3V0drPJCOQfY5Rp","gameId":"s3V0drPJCOQfY5Rp","gameDescription":"60 sec. No move","playedWithEliminations":false,"forbidMoving":true,"forbidRotating":false,"forbidZooming":false,"timeLimit":60},{"allGuesses":[[{"playerName":"joseph","playerId":"633342fdc47eb0d4a0b70f24","roundScoreInPoints":869,"distanceInMeters":3242773.244651547,"time":18,"lat":-29.77567851195815,"lng":-53.74174451311175},{"playerName":"MrYog ","playerId":"5c4cb5303d925b4af4b898ec","roundScoreInPoints":892,"distanceInMeters":3195366.2725749467,"time":10,"lat":-29.206116023537366,"lng":-53.76176648694899},{"playerName":"sunkencity64","playerId":"5ee958f607039a72c8609710","roundScoreInPoints":3422,"distanceInMeters":702843.6010293472,"time":19,"lat":-5.938370549055037,"lng":-41.94219296487611},{"playerName":"sgminer21","playerId":"56af8726f0f544f19cb8a9ea","roundScoreInPoints":860,"distanceInMeters":3263117.055377056,"time":28,"lat":-29.241974541920534,"lng":-54.77877289752059}],[{"playerName":"joseph","playerId":"633342fdc47eb0d4a0b70f24","roundScoreInPoints":4450,"distanceInMeters":215881.83581702,"time":9,"lat":57.644968087824665,"lng":18.634452618984543},{"playerName":"MrYog ","playerId":"5c4cb5303d925b4af4b898ec","roundScoreInPoints":4897,"distanceInMeters":38705.1141222878,"time":8,"lat":58.176452314575116,"lng":14.902244689466752},{"playerName":"sunkencity64","playerId":"5ee958f607039a72c8609710","roundScoreInPoints":3516,"distanceInMeters":652692.2667322409,"time":7,"lat":62.258525889957205,"lng":22.761597965126725},{"playerName":"sgminer21","playerId":"56af8726f0f544f19cb8a9ea","roundScoreInPoints":2689,"distanceInMeters":1149836.3683645073,"time":51,"lat":66.49169320463214,"lng":27.277885644727714}],[{"playerName":"joseph","playerId":"633342fdc47eb0d4a0b70f24","roundScoreInPoints":4682,"distanceInMeters":121769.2864702272,"time":12,"lat":33.054841200792524,"lng":130.95889240680538},{"playerName":"MrYog ","playerId":"5c4cb5303d925b4af4b898ec","roundScoreInPoints":4670,"distanceInMeters":126507.7049874516,"time":9,"lat":33.159258520149734,"lng":131.80257925166202},{"playerName":"sunkencity64","playerId":"5ee958f607039a72c8609710","roundScoreInPoints":3070,"distanceInMeters":903827.8552186686,"time":8,"lat":37.347724219086146,"lng":138.99513230696985},{"playerName":"sgminer21","playerId":"56af8726f0f544f19cb8a9ea","roundScoreInPoints":2551,"distanceInMeters":1247630.04949955,"time":29,"lat":40.43759961993825,"lng":140.75567806319265}],[{"playerName":"joseph","playerId":"633342fdc47eb0d4a0b70f24","roundScoreInPoints":4467,"distanceInMeters":208898.246223411,"time":10,"lat":46.65853251042208,"lng":2.388540274705071},{"playerName":"MrYog ","playerId":"5c4cb5303d925b4af4b898ec","roundScoreInPoints":3975,"distanceInMeters":425070.9162610442,"time":6,"lat":44.35475883800517,"lng":0.05062848239549389},{"playerName":"sunkencity64","playerId":"5ee958f607039a72c8609710","roundScoreInPoints":4077,"distanceInMeters":378135.556287877,"time":6,"lat":48.32180681519574,"lng":5.802373085129111},{"playerName":"sgminer21","playerId":"56af8726f0f544f19cb8a9ea","roundScoreInPoints":4360,"distanceInMeters":254070.1467035192,"time":17,"lat":49.75150462477061,"lng":3.185788897557482}],[{"playerName":"joseph","playerId":"633342fdc47eb0d4a0b70f24","roundScoreInPoints":4865,"distanceInMeters":50919.9090799203,"time":10,"lat":40.711258907033226,"lng":14.766244210315701},{"playerName":"MrYog ","playerId":"5c4cb5303d925b4af4b898ec","roundScoreInPoints":4094,"distanceInMeters":370744.9289032346,"time":11,"lat":44.08976175901411,"lng":12.521286084352061},{"playerName":"sunkencity64","playerId":"5ee958f607039a72c8609710","roundScoreInPoints":4153,"distanceInMeters":344150.0664860318,"time":15,"lat":43.01334371105316,"lng":11.133298742884183},{"playerName":"sgminer21","playerId":"56af8726f0f544f19cb8a9ea","roundScoreInPoints":4339,"distanceInMeters":262953.933728419,"time":20,"lat":40.834420388077135,"lng":17.45833809730913}]],"playerGames":[{"player":"joseph","playerId":"633342fdc47eb0d4a0b70f24","points":19333,"r1":{"points":869,"time":18},"r2":{"points":4450,"time":9},"r3":{"points":4682,"time":12},"r4":{"points":4467,"time":10},"r5":{"points":4865,"time":10},"eliminatedInGame":null,"totalDistanceInMeters":3840242.522242126,"totalTime":59,"pinUrl":"pin/8d83e2b6656dcb6de58d553a9e822aed.png"},{"player":"MrYog ","playerId":"5c4cb5303d925b4af4b898ec","points":18528,"r1":{"points":892,"time":10},"r2":{"points":4897,"time":8},"r3":{"points":4670,"time":9},"r4":{"points":3975,"time":6},"r5":{"points":4094,"time":11},"eliminatedInGame":null,"totalDistanceInMeters":4156394.936848965,"totalTime":43,"pinUrl":"pin/1b085ff7a2c27a4441e137a0067ea11c.png"},{"player":"sunkencity64","playerId":"5ee958f607039a72c8609710","points":18238,"r1":{"points":3422,"time":19},"r2":{"points":3516,"time":7},"r3":{"points":3070,"time":8},"r4":{"points":4077,"time":6},"r5":{"points":4153,"time":15},"eliminatedInGame":null,"totalDistanceInMeters":2981649.345754165,"totalTime":55,"pinUrl":"pin/8ab07260821827d1947dfc4894297cec.png"},{"player":"sgminer21","playerId":"56af8726f0f544f19cb8a9ea","points":14799,"r1":{"points":860,"time":28},"r2":{"points":2689,"time":51},"r3":{"points":2551,"time":29},"r4":{"points":4360,"time":17},"r5":{"points":4339,"time":20},"eliminatedInGame":null,"totalDistanceInMeters":6177607.553673051,"totalTime":146,"pinUrl":"pin/c00414d324e98770adefeef7cef0161e.png"}],"answers":[{"lat":-6.150359062715608,"lng":-35.589568403281,"countryCode":null,"countryName":null},{"lat":57.833435805227715,"lng":15.013930876640954,"countryCode":null,"countryName":null},{"lat":32.0534791406846,"lng":131.4848376176476,"countryCode":null,"countryName":null},{"lat":48.15090833910587,"lng":0.7022445554194737,"countryCode":null,"countryName":null},{"lat":41.035994861483516,"lng":14.33924271717008,"countryCode":null,"countryName":null}],"mapName":"A Diverse World (Unmaintained)","gameNumber":1,"gameUrl":"https://www.geoguessr.com/results/o48RBbZjDJUpjF5D","gameId":"o48RBbZjDJUpjF5D","gameDescription":"60 sec. No move","playedWithEliminations":false,"forbidMoving":true,"forbidRotating":false,"forbidZooming":false,"timeLimit":60}]}